{
  "data_asset_type": null,
  "expectation_suite_name": "NEXRAD_suite",
  "expectations": [
    {
      "expectation_type": "expect_table_row_count_to_be_between",
      "kwargs": {
        "max_value": 1000000,
        "min_value": 0
      },
      "meta": {
        "profiler_details": {
          "metric_configuration": {
            "domain_kwargs": {},
            "metric_name": "table.row_count",
            "metric_value_kwargs": null
          },
          "num_batches": 1
        }
      }
    },
    {
      "expectation_type": "expect_table_columns_to_match_set",
      "kwargs": {
        "column_set": [
          "station",
          "year",
          "month",
          "day"
        ]
      },
      "meta": {
        "profiler_details": {
          "success_ratio": 1.0
        }
      }
    },
    {
      "expectation_type": "expect_column_values_to_be_in_set",
      "kwargs": {
        "column": "year",
        "value_set": [
          "2022",
          "2023"
        ]
      },
      "meta": {}
    },
    {
      "expectation_type": "expect_column_values_to_not_be_null",
      "kwargs": {
        "column": "month"
      },
      "meta": {
        "profiler_details": {
          "metric_configuration": {
            "domain_kwargs": {
              "column": "month"
            },
            "metric_dependencies": null,
            "metric_name": "column_values.nonnull.unexpected_count",
            "metric_value_kwargs": null
          },
          "num_batches": 1
        }
      }
    },
    {
      "expectation_type": "expect_column_values_to_not_be_null",
      "kwargs": {
        "column": "station"
      },
      "meta": {
        "profiler_details": {
          "metric_configuration": {
            "domain_kwargs": {
              "column": "station"
            },
            "metric_dependencies": null,
            "metric_name": "column_values.nonnull.unexpected_count",
            "metric_value_kwargs": null
          },
          "num_batches": 1
        }
      }
    },
    {
      "expectation_type": "expect_column_values_to_not_be_null",
      "kwargs": {
        "column": "day"
      },
      "meta": {
        "profiler_details": {
          "metric_configuration": {
            "domain_kwargs": {
              "column": "day"
            },
            "metric_dependencies": null,
            "metric_name": "column_values.nonnull.unexpected_count",
            "metric_value_kwargs": null
          },
          "num_batches": 1
        }
      }
    },
    {
      "expectation_type": "expect_column_values_to_not_be_null",
      "kwargs": {
        "column": "year"
      },
      "meta": {
        "profiler_details": {
          "metric_configuration": {
            "domain_kwargs": {
              "column": "year"
            },
            "metric_dependencies": null,
            "metric_name": "column_values.nonnull.unexpected_count",
            "metric_value_kwargs": null
          },
          "num_batches": 1
        }
      }
    },
    {
      "expectation_type": "expect_column_values_to_be_between",
      "kwargs": {
        "column": "month",
        "max_value": 12,
        "min_value": 1
      },
      "meta": {}
    },
    {
      "expectation_type": "expect_column_values_to_be_between",
      "kwargs": {
        "column": "day",
        "max_value": 31,
        "min_value": 1
      },
      "meta": {}
    }
  ],
  "ge_cloud_id": null,
  "meta": {
    "citations": [
      {
        "citation_date": "2023-02-10T17:16:22.894705Z",
        "comment": "Created by effective Rule-Based Profiler of OnboardingDataAssistant with the configuration included.\n"
      }
    ],
    "great_expectations_version": "0.15.48"
  }
}